swarmauri_publisher_rabbitmq/RabbitMQPublisher.py
swarmauri_publisher_rabbitmq/__init__.py
swarmauri_publisher_rabbitmq-0.3.0.dev4.dist-info/METADATA
swarmauri_publisher_rabbitmq-0.3.0.dev4.dist-info/WHEEL
swarmauri_publisher_rabbitmq-0.3.0.dev4.dist-info/entry_points.txt
swarmauri_publisher_rabbitmq-0.3.0.dev4.dist-info/RECORD
